pynarist/__init__.py
pynarist/_errors.py
pynarist/_impls.py
pynarist/inspections.py
pynarist/model.py
pynarist-0.1.1.dist-info/LICENSE
pynarist-0.1.1.dist-info/METADATA
pynarist-0.1.1.dist-info/NOTICE.txt
pynarist-0.1.1.dist-info/WHEEL
pynarist-0.1.1.dist-info/RECORD
