Metadata-Version: 2.1
Name: pynarist
Version: 0.1.1
Summary: A Python library for parsing and building binary data.
License: Apache-2.0
Author: Temps233
Author-email: temps233@outlook.com
Requires-Python: >=3.11,<4.0
Classifier: License :: OSI Approved :: Apache Software License
Classifier: Programming Language :: Python :: 3
Classifier: Programming Language :: Python :: 3.11
Classifier: Programming Language :: Python :: 3.12
